gobjects/__init__.py
gobjects/core/__init__.py
gobjects/core/bed.py
gobjects/core/bedpe.py
gobjects/core/gtf.py
gobjects/core/intervalmap.py
gobjects/core/intervals.py
gobjects/operations/__init__.py
gobjects/operations/intersect.py
gobjects/operations/writers.py
gobjects-0.0.9.dist-info/METADATA
gobjects-0.0.9.dist-info/WHEEL
gobjects-0.0.9.dist-info/top_level.txt
gobjects-0.0.9.dist-info/RECORD
